mlmonitor/MANIFEST.in
mlmonitor/__init__.py
mlmonitor/config.py
mlmonitor/credentials_example.cfg
mlmonitor/exceptions.py
mlmonitor/setup.py
mlmonitor/version.meta
mlmonitor/custmonitor/README.md
mlmonitor/custmonitor/__init__.py
mlmonitor/custmonitor/metrics/__init__.py
mlmonitor/custmonitor/metrics/use_case_churn.py
mlmonitor/custmonitor/metrics/use_case_gcr.py
mlmonitor/custmonitor/metricsprovider/__init__.py
mlmonitor/custmonitor/metricsprovider/helpers.py
mlmonitor/custmonitor/tests/unit/config/.gitkeep
mlmonitor/data/__init__.py
mlmonitor/data/cos.py
mlmonitor/datasets/.gitkeep
mlmonitor/datasets/churn/.gitkeep
mlmonitor/datasets/churn/churn.txt
mlmonitor/datasets/churn/feedback_logging_churn.csv
mlmonitor/datasets/churn/feedback_logging_no_preds_churn.csv
mlmonitor/datasets/churn/feedback_logging_preds_churn.csv
mlmonitor/datasets/churn/train.csv
mlmonitor/datasets/churn/validation.csv
mlmonitor/datasets/gcr/.gitkeep
mlmonitor/datasets/gcr/gcr_explicit_payload_logging.csv
mlmonitor/datasets/gcr/gcr_feedback_logging_aws.csv
mlmonitor/datasets/gcr/gcr_feedback_logging_with_pred_aws.csv
mlmonitor/datasets/gcr/gcr_feedback_logging_with_pred_aws2.csv
mlmonitor/datasets/gcr/german_credit_data_biased_training.csv
mlmonitor/datasets/gcr/test_feedback_data_gcr.csv
mlmonitor/datasets/mnist/.gitkeep
mlmonitor/datasets/mnist/mnist_feedback_20_with_pred_aws.csv
mlmonitor/datasets/mnist/t10k-images-idx3-ubyte.gz
mlmonitor/datasets/mnist/t10k-labels-idx1-ubyte.gz
mlmonitor/datasets/mnist/train-images-idx3-ubyte.gz
mlmonitor/datasets/mnist/train-labels-idx1-ubyte.gz
mlmonitor/figures/.gitkeep
mlmonitor/models/.gitkeep
mlmonitor/models/model_churn/.gitkeep
mlmonitor/models/model_churn/xgboost-model-bst
mlmonitor/models/model_churn/xgboost-model-sk
mlmonitor/models/model_gcr/.gitkeep
mlmonitor/models/model_mnist/.gitkeep
mlmonitor/src/__init__.py
mlmonitor/src/aws/__init__.py
mlmonitor/src/aws/deploy_sagemaker_endpoint.py
mlmonitor/src/aws/deployment.py
mlmonitor-1.0.30.dist-info/METADATA
mlmonitor-1.0.30.dist-info/WHEEL
mlmonitor-1.0.30.dist-info/top_level.txt
mlmonitor-1.0.30.dist-info/RECORD
