Metadata-Version: 2.4
Name: mlmonitor
Version: 1.0.30
Summary: Orchestration of model use cases
Home-page: https://github.com/IBM/mlmonitor/mlmonitor
Author: Jacques-Sylvain Lecointre
Author-email: js.lecointre@ibm.com
Requires-Python: >=3.10.4
Requires-Dist: ibm_watson_openscale==3.1.3
Requires-Dist: ibm_watsonx_ai==1.4.11
Requires-Dist: ipython==9.8.0
Requires-Dist: ibm-aigov-facts-client==1.0.207
Requires-Dist: pygit2
Provides-Extra: local
Requires-Dist: pip; extra == "local"
Requires-Dist: numpy<2.0,>=1.23; extra == "local"
Requires-Dist: boto3<2.0,>=1.34.94; extra == "local"
Requires-Dist: scikit-learn<2.0,>=1.3.1; extra == "local"
Requires-Dist: joblib==1.1.1; extra == "local"
Requires-Dist: matplotlib; extra == "local"
Provides-Extra: dev
Requires-Dist: PyYAML; extra == "dev"
Requires-Dist: wheel; extra == "dev"
Requires-Dist: jupyterlab; extra == "dev"
Requires-Dist: pre-commit; extra == "dev"
Requires-Dist: twine; extra == "dev"
Requires-Dist: python-dotenv; extra == "dev"
Provides-Extra: azure
Requires-Dist: azureml-sdk==1.61.0; extra == "azure"
Provides-Extra: sagemaker
Requires-Dist: sagemaker==2.255.0; extra == "sagemaker"
Provides-Extra: drift
Requires-Dist: ibm-wos-utils==5.3.0.10; extra == "drift"
Dynamic: author
Dynamic: author-email
Dynamic: description
Dynamic: description-content-type
Dynamic: home-page
Dynamic: provides-extra
Dynamic: requires-dist
Dynamic: requires-python
Dynamic: summary
